{"id":10000352,"name":"苏恩","nameEn":"Suen","quality":"ssr","views":[{"id":11000129,"name":"默认","hasState2":true}],"line":1,"side":{"sort":5,"name":"索思学会"},"attr":{"hp":7500.0,"def":85.0,"atk":75.0,"atkSpeed":100.0,"luck":0.0,"costRestorePerFrame":0.0022,"costRestore":0.134},"growth":{"hp":750.0,"atk":7.5,"def":8.5},"homeSkills":[{"id":83900085,"name":"提神秘方","desc":"疲劳值上限+8","tag":4,"nextIndex":0,"resonanceLv":1},{"id":83900154,"name":"精神训练","desc":"澄明度上限+4","tag":4,"nextIndex":3,"resonanceLv":4},{"id":83900155,"name":"精神训练+","desc":"澄明度上限+4","tag":4,"nextIndex":-1,"resonanceLv":5}],"foods":[{"id":83300002,"name":"菜肉俱全汉堡","energy":20,"rewards":[{"id":11700013,"name":"经典宠物口粮","quality":"n","des":"使用后可增加500单位口粮，\\n每日宠物亲密度获取+6。","saleType":"NotSale"}],"expirationDate":3,"letter":"不是特意给你做的，可别误会了！"}],"birthday":"2月9日","gender":"女","height":"152cm","birthplace":"铁山城","identity":"索思学会·御敌枢纽","ability":"恢复&肉体强化","resume":[{"des":"来自索思学会的少女，最令人难忘的特征是其遍布身体的奇异纹路。虽然从年龄上来看还只是个孩子，但各项检测结果表示她拥有着接近成人的素质，她也因此总是以大人的身份自居着。无论是在学会，还是在列车上，十分自来熟的苏恩遇到谁都能抓着对方说个不停。如果有人对她身上的纹路产生好奇，苏恩会不加掩饰地，骄傲地炫耀给对方看。"}]}